tokeniser/__init__.py
tokeniser/tokeniser.py
tokeniser-2025.5.190811.dist-info/licenses/LICENSE
tokeniser-2025.5.190811.dist-info/METADATA
tokeniser-2025.5.190811.dist-info/WHEEL
tokeniser-2025.5.190811.dist-info/top_level.txt
tokeniser-2025.5.190811.dist-info/RECORD
